controller/controller.v
// Instruction format [Op code, 4][Operand B, 8][Operand A, 8]

module controller(
  input wire clk, reset,
  input wire [3:0] opcode,
  input wire op,
  output reg [2:0] alu_signals,
  output reg acc_load, acc_mux
);

  localparam [1:0] no_op = 2'b00, 
                   decode = 2'b01,
                   execute = 2'b10;

  localparam [3:0] add   = 4'b0000,
                   add_a = 4'b0001,
                   sub   = 4'b0010,
                   sub_a = 4'b0011,
                   and_  = 4'b0100,
                   and_a = 4'b0101,
                   or_   = 4'b0110,
                   or_a  = 4'b0111,
                   shr   = 4'b1000;

  reg [1:0] state_reg, state_next;

  always @(posedge clk, posedge reset)
    if (reset) 
    begin
      state_reg <= no_op;
    end
    else
    begin
      state_reg <= state_next;
    end

  always @*
  begin
    state_next = state_reg;
    acc_load = 1'b0;

    case (state_reg)
      no_op:
        if (op)
          state_next = decode;
      decode:
      begin
        state_next = execute;
        case (opcode)
          add:
          begin
            alu_signals = 3'b000; // Chooses the add operation
            acc_mux = 0;  // Takes input from A and B
          end

          add_a:
          begin
            alu_signals = 3'b000; // Chooses the add operation
            acc_mux = 1;  // Takes input from A and B
          end

          sub:
          begin
            alu_signals = 3'b001; // Chooses the add operation
            acc_mux = 0;  // Takes input from A and B
          end

          sub_a:
          begin
            alu_signals = 3'b001; // Chooses the add operation
            acc_mux = 1;  // Takes input from A and B
          end

          and_:
          begin
            alu_signals = 3'b010; // Chooses the add operation
            acc_mux = 0;  // Takes input from A and B
          end

          and_a:
          begin
            alu_signals = 3'b010; // Chooses the add operation
            acc_mux = 1;  // Takes input from A and B
          end

          or_:
          begin
            alu_signals = 3'b011; // Chooses the add operation
            acc_mux = 0;  // Takes input from A and B
          end

          or_a:
          begin
            alu_signals = 3'b011; // Chooses the add operation
            acc_mux = 1;  // Takes input from A and B
          end

          shr:
          begin
            alu_signals = 3'b100;
            acc_mux = 0;
          end

          default:
            state_next = no_op;
        endcase
      end

      execute:
      begin
        acc_load = 1'b1;
        state_next = no_op;
      end
    endcase
  end


endmodule

controller/controller_tb.v
`timescale 1ns/1ps

module controller_tb;

  integer i, a;
  localparam T = 20;

  localparam [3:0] add   = 4'b0000,
                   add_a = 4'b0001,
                   sub   = 4'b0010,
                   sub_a = 4'b0011,
                   and_  = 4'b0100,
                   and_a = 4'b0101,
                   or_   = 4'b0110,
                   or_a  = 4'b0111,
                   shr   = 4'b1000;

  reg clk, reset;
  reg [3:0] opcode;
  reg op;
  wire [2:0] alu_signals;
  wire acc_load, acc_mux;

  controller uut(
    .clk(clk), .reset(reset),
    .opcode(opcode),
    .op(op),
    .alu_signals(alu_signals),
    .acc_load(acc_load), .acc_mux(acc_mux)
  );

  always
  begin
    clk = 1'b1;
    #(T/2);
    clk = 1'b0;
    #(T/2);
  end

  initial
  begin
    reset = 1'b1;
    #(T/2);
    reset = 1'b0;
  end

  initial
  begin
    $dumpfile("controller.vcd");
    $dumpvars(1, uut);

    op = 1'b0;

    @(negedge reset);
    @(negedge clk);
    a = 0;
    for (i = 0; i < 10; i = i + 1)
    begin
      opcode = a;
      a = a + 1;
      op = 1'b1;

      @(negedge clk);
      op = 1'b0;
      repeat(2) @(negedge clk);
    end

    $finish;
  end

endmodule

controller/controller.vcd
$date
	Wed Jul 23 19:21:53 2025
$end
$version
	Icarus Verilog
$end
$timescale
	1ps
$end
$scope module controller_tb $end
$scope module uut $end
$var wire 1 ! clk $end
$var wire 1 " op $end
$var wire 4 # opcode [3:0] $end
$var wire 1 $ reset $end
$var parameter 4 % add $end
$var parameter 4 & add_a $end
$var parameter 4 ' and_ $end
$var parameter 4 ( and_a $end
$var parameter 2 ) decode $end
$var parameter 2 * execute $end
$var parameter 2 + no_op $end
$var parameter 4 , or_ $end
$var parameter 4 - or_a $end
$var parameter 4 . shr $end
$var parameter 4 / sub $end
$var parameter 4 0 sub_a $end
$var reg 1 1 acc_load $end
$var reg 1 2 acc_mux $end
$var reg 3 3 alu_signals [2:0] $end
$var reg 2 4 state_next [1:0] $end
$var reg 2 5 state_reg [1:0] $end
$upscope $end
$upscope $end
$enddefinitions $end
$comment Show the parameter values. $end
$dumpall
b11 0
b10 /
b1000 .
b111 -
b110 ,
b0 +
b10 *
b1 )
b101 (
b100 '
b1 &
b0 %
$end
#0
$dumpvars
b0 5
b0 4
bx 3
x2
01
1$
bx #
0"
1!
$end
#10000
0$
0!
#20000
1!
#30000
b1 4
1"
b0 #
0!
#40000
02
b0 3
b10 4
b1 5
1!
#50000
b10 4
0"
0!
#60000
b0 4
11
b10 5
1!
#70000
0!
#80000
01
b0 5
1!
#90000
b1 4
1"
b1 #
0!
#100000
12
b10 4
b1 5
1!
#110000
b10 4
0"
0!
#120000
b0 4
11
b10 5
1!
#130000
0!
#140000
01
b0 5
1!
#150000
b1 4
1"
b10 #
0!
#160000
02
b1 3
b10 4
b1 5
1!
#170000
b10 4
0"
0!
#180000
b0 4
11
b10 5
1!
#190000
0!
#200000
01
b0 5
1!
#210000
b1 4
1"
b11 #
0!
#220000
12
b10 4
b1 5
1!
#230000
b10 4
0"
0!
#240000
b0 4
11
b10 5
1!
#250000
0!
#260000
01
b0 5
1!
#270000
b1 4
1"
b100 #
0!
#280000
02
b10 3
b10 4
b1 5
1!
#290000
b10 4
0"
0!
#300000
b0 4
11
b10 5
1!
#310000
0!
#320000
01
b0 5
1!
#330000
b1 4
1"
b101 #
0!
#340000
12
b10 4
b1 5
1!
#350000
b10 4
0"
0!
#360000
b0 4
11
b10 5
1!
#370000
0!
#380000
01
b0 5
1!
#390000
b1 4
1"
b110 #
0!
#400000
02
b11 3
b10 4
b1 5
1!
#410000
b10 4
0"
0!
#420000
b0 4
11
b10 5
1!
#430000
0!
#440000
01
b0 5
1!
#450000
b1 4
1"
b111 #
0!
#460000
12
b10 4
b1 5
1!
#470000
b10 4
0"
0!
#480000
b0 4
11
b10 5
1!
#490000
0!
#500000
01
b0 5
1!
#510000
b1 4
1"
b1000 #
0!
#520000
02
b100 3
b10 4
b1 5
1!
#530000
b10 4
0"
0!
#540000
b0 4
11
b10 5
1!
#550000
0!
#560000
01
b0 5
1!
#570000
b1 4
1"
b1001 #
0!
#580000
b0 4
b1 5
1!
#590000
b0 4
0"
0!
#600000
b0 5
1!
